Metadata-Version: 2.4
Name: tkeditor
Version: 0.1.1
Summary: A Python editor with syntax highlighting, folding, line numbers, and bracket tracking
Author-email: Anmol Kumar <ask995844@gmail.com>
License: MIT License
Project-URL: Homepage, https://github.com/TechRuler/tkeditor
Requires-Python: >=3.9
License-File: LICENSE
Dynamic: license-file
